seqlbtoolkit/__init__.py
seqlbtoolkit/data.py
seqlbtoolkit/embs.py
seqlbtoolkit/io.py
seqlbtoolkit/text.py
seqlbtoolkit/timer.py
seqlbtoolkit/utils.py
seqlbtoolkit/training/__init__.py
seqlbtoolkit/training/config.py
seqlbtoolkit/training/eval.py
seqlbtoolkit/training/output.py
seqlbtoolkit/training/status.py
seqlbtoolkit/training/train.py
seqlbtoolkit/training/dataset/__init__.py
seqlbtoolkit/training/dataset/base_dataset.py
seqlbtoolkit/training/dataset/batching.py
seqlbtoolkit/training/dataset/ner_dataset.py
seqlbtoolkit/training/dataset/utils.py
seqlbtoolkit-0.6.18.dist-info/licenses/LICENSE
seqlbtoolkit-0.6.18.dist-info/METADATA
seqlbtoolkit-0.6.18.dist-info/WHEEL
seqlbtoolkit-0.6.18.dist-info/top_level.txt
seqlbtoolkit-0.6.18.dist-info/RECORD
