Metadata-Version: 2.4
Name: SeqLbToolkit
Version: 0.6.18
Summary: Commonly-used functions for building sequence labeling models.
Home-page: https://github.com/Yinghao-Li/seqlbtoolkit
Author: Yinghao Li
Author-email: yinghaoli@gatech.edu
License: MIT
Keywords: nlp,sequence-labeling,ml,machine-learning,natural-language-processing
Classifier: Intended Audience :: Developers
Classifier: Intended Audience :: Science/Research
Classifier: License :: OSI Approved :: MIT License
Classifier: Operating System :: OS Independent
Classifier: Programming Language :: Python :: 3
Classifier: Topic :: Text Processing
Classifier: Topic :: Text Processing :: Linguistic
Requires-Python: >=3.9
License-File: LICENSE
Dynamic: author
Dynamic: author-email
Dynamic: classifier
Dynamic: description
Dynamic: description-content-type
Dynamic: home-page
Dynamic: keywords
Dynamic: license
Dynamic: license-file
Dynamic: requires-python
Dynamic: summary
